searcherator/__init__.py
searcherator/searcherator.py
searcherator-0.0.1.dist-info/METADATA
searcherator-0.0.1.dist-info/WHEEL
searcherator-0.0.1.dist-info/top_level.txt
searcherator-0.0.1.dist-info/RECORD
