Metadata-Version: 2.4
Name: searcherator
Version: 0.0.1
Summary: A Python package for performing cached web searches using the Brave Search API
Author-email: Arved Klöhn <arved.kloehn@gmail.com>
Project-URL: Homepage, https://github.com/Redundando/searcherator
Project-URL: Bug Tracker, https://github.com/Redundando/searcherator/issues
Classifier: Programming Language :: Python :: 3
Classifier: License :: OSI Approved :: MIT License
Classifier: Operating System :: OS Independent
Requires-Python: >=3.8
Requires-Dist: cacherator
Requires-Dist: logorator
Requires-Dist: aiohttp
